csv_to_custom_json/__init__.py
csv_to_custom_json-1.0.0.dist-info/LICENSE
csv_to_custom_json-1.0.0.dist-info/METADATA
csv_to_custom_json-1.0.0.dist-info/WHEEL
csv_to_custom_json-1.0.0.dist-info/top_level.txt
csv_to_custom_json-1.0.0.dist-info/RECORD
