Metadata-Version: 2.1
Name: csv-to-custom-json
Version: 1.0.0
Summary: Easily convert your CSV to custom JSON
Author-email: n4n5 <its.just.n4n5@gmail.com>
License: MIT License
Project-URL: Homepage, https://github.com/its-just-nans/csv-to-custom-json-python
Project-URL: Bug Tracker, https://github.com/its-just-nans/csv-to-custom-json-python/issues
Keywords: csv,custom_json,custom-json,json,csv-to-json,csv_to_json,convert,convert-json,convert_json,convert-to-json,convert_to_json,to-json,to_json,csv-to-custom-json,csv_to_custom_json
Classifier: License :: OSI Approved :: MIT License
Classifier: Programming Language :: Python
Classifier: Programming Language :: Python :: 3
Requires-Python: >=3.6
License-File: LICENSE
